tech_shrimp_mcp_server/__init__.py
tech_shrimp_mcp_server-0.1.1.dist-info/METADATA
tech_shrimp_mcp_server-0.1.1.dist-info/WHEEL
tech_shrimp_mcp_server-0.1.1.dist-info/entry_points.txt
tech_shrimp_mcp_server-0.1.1.dist-info/RECORD
