Metadata-Version: 2.4
Name: tech-shrimp-mcp-server
Version: 0.1.1
Summary: Add your description here
Author-email: tech-shrimp <techshrimp@163.com>
Requires-Python: >=3.11
Requires-Dist: mcp>=1.0.0
